{
  "db_name": "PostgreSQL",
  "query": "SELECT id, user_id, title, message, notification_type, priority, status, \n                      metadata, read_at, created_at, updated_at\n               FROM notifications \n               WHERE user_id = $1\n               ORDER BY created_at DESC\n               LIMIT $2 OFFSET $3",
  "describe": {
    "columns": [
      {
        "ordinal": 0,
        "name": "id",
        "type_info": "Uuid"
      },
      {
        "ordinal": 1,
        "name": "user_id",
        "type_info": "Uuid"
      },
      {
        "ordinal": 2,
        "name": "title",
        "type_info": "Varchar"
      },
      {
        "ordinal": 3,
        "name": "message",
        "type_info": "Text"
      },
      {
        "ordinal": 4,
        "name": "notification_type",
        "type_info": "Varchar"
      },
      {
        "ordinal": 5,
        "name": "priority",
        "type_info": "Varchar"
      },
      {
        "ordinal": 6,
        "name": "status",
        "type_info": "Varchar"
      },
      {
        "ordinal": 7,
        "name": "metadata",
        "type_info": "Jsonb"
      },
      {
        "ordinal": 8,
        "name": "read_at",
        "type_info": "Timestamptz"
      },
      {
        "ordinal": 9,
        "name": "created_at",
        "type_info": "Timestamptz"
      },
      {
        "ordinal": 10,
        "name": "updated_at",
        "type_info": "Timestamptz"
      }
    ],
    "parameters": {
      "Left": [
        "Uuid",
        "Int8",
        "Int8"
      ]
    },
    "nullable": [
      false,
      false,
      false,
      false,
      false,
      false,
      false,
      true,
      true,
      false,
      false
    ]
  },
  "hash": "4fda47a2243e1d0c17d5d11c655e2d63036841af0e52d531bfa79accb80b27fe"
}
